misaka/api.py
misaka/callbacks.py
misaka/constants.py
misaka/utils.py
misaka/_hoedown.pyd
misaka/__init__.py
misaka-2.0.0.data/scripts/misaka
misaka-2.0.0.dist-info/DESCRIPTION.rst
misaka-2.0.0.dist-info/METADATA
misaka-2.0.0.dist-info/metadata.json
misaka-2.0.0.dist-info/RECORD
misaka-2.0.0.dist-info/top_level.txt
misaka-2.0.0.dist-info/WHEEL
